bullinv_api_client/__init__.py
bullinv_api_client/exceptions.py
bullinv_api_client/logger.py
bullinv_api_client/questdb.py
bullinv_api_client/websocket/__init__.py
bullinv_api_client/websocket/common.py
bullinv_api_client/websocket/models.py
bullinv_api_client/websocket/parsers.py
bullinv_api_client-0.1.2.dist-info/METADATA
bullinv_api_client-0.1.2.dist-info/WHEEL
bullinv_api_client-0.1.2.dist-info/top_level.txt
bullinv_api_client-0.1.2.dist-info/RECORD
