Metadata-Version: 2.4
Name: bullinv-api-client
Version: 0.1.2
Summary: Add your description here
Requires-Python: >=3.10
Requires-Dist: websockets>=12.0
Requires-Dist: websocket-client>=1.7.0
Requires-Dist: certifi>=2025.8.3
Requires-Dist: requests>=2.31.0
Requires-Dist: pandas>=2.0.0
Requires-Dist: python-dotenv>=1.0.0
